Metadata-Version: 2.1
Name: syncvtools
Version: 0.1.13
Summary: CV Tools related to Object Detection
Home-page: UNKNOWN
Author: Aleksandr Patsekin
Author-email: apatsekin@gmail.com
License: UNKNOWN
Platform: UNKNOWN
Classifier: Programming Language :: Python :: 3
Classifier: License :: Other/Proprietary License
Classifier: Operating System :: OS Independent
Requires-Python: >=3.0
Requires-Dist: opencv-python
Requires-Dist: lxml
Requires-Dist: Pillow
Requires-Dist: boto3
Requires-Dist: tqdm
Requires-Dist: pyyaml
Requires-Dist: scipy
